{"trial_id": "005", "hyperparameters": {"space": [{"class_name": "Int", "config": {"name": "lstm_units", "default": null, "conditions": [], "min_value": 32, "max_value": 512, "step": 32, "sampling": "linear"}}, {"class_name": "Float", "config": {"name": "l1_regularization", "default": 0.0001, "conditions": [], "min_value": 1e-05, "max_value": 0.01, "step": null, "sampling": "log"}}, {"class_name": "Float", "config": {"name": "l2_regularization", "default": 0.0001, "conditions": [], "min_value": 1e-05, "max_value": 0.01, "step": null, "sampling": "log"}}], "values": {"lstm_units": 384, "l1_regularization": 0.00020087857375925783, "l2_regularization": 0.00014616157894890226}}, "metrics": {"metrics": {"loss": {"direction": "min", "observations": [{"value": [33.44255447387695], "step": 46}]}, "custom_mape": {"direction": "min", "observations": [{"value": [32.922760009765625], "step": 46}]}, "custom_mae": {"direction": "min", "observations": [{"value": [7.194735050201416], "step": 46}]}, "val_loss": {"direction": "min", "observations": [{"value": [12.680712699890137], "step": 46}]}, "val_custom_mape": {"direction": "min", "observations": [{"value": [12.56525707244873], "step": 46}]}, "val_custom_mae": {"direction": "min", "observations": [{"value": [5.540000915527344], "step": 46}]}}}, "score": 12.56525707244873, "best_step": 46, "status": "COMPLETED", "message": null}